{
    "search": {
        "columns": [
            "src_ip", 
            "src_port", 
            "dest_ip", 
            "dest_port", 
            "ldap.full_message.message_type.searchResDone.matched_dn", 
            "ldap.full_message.message_type.searchResDone.response_code"
        ], 
        "description": "", 
        "hits": 0, 
        "kibanaSavedObjectMeta": {
            "searchSourceJSON": "{\"index\":\"910957e0-dee0-11e9-8b38-bbc335ba1a14\",\"highlightAll\":true,\"version\":true,\"query\":{\"language\":\"lucene\",\"query\":\"\"},\"filter\":[]}"
        }, 
        "sort": [
            "@timestamp", 
            "desc"
        ], 
        "title": "LDAP-EventsList", 
        "version": 1
    }, 
    "type": "search", 
    "updated_at": "2019-10-06T09:51:25.502Z"
}