{
    "migrationVersion": {
        "visualization": "6.7.2"
    }, 
    "type": "visualization", 
    "updated_at": "2019-10-06T09:52:16.522Z", 
    "visualization": {
        "description": "", 
        "kibanaSavedObjectMeta": {
            "searchSourceJSON": "{\"index\":\"defa6c90-cae7-11e8-9f69-c36de0ada098\",\"query\":{\"query\":\"\",\"language\":\"lucene\"},\"filter\":[]}"
        }, 
        "title": "KRB5-BySname", 
        "uiStateJSON": "{}", 
        "version": 1, 
        "visState": "{\"title\":\"KRB5-BySname\",\"type\":\"pie\",\"params\":{\"type\":\"pie\",\"addTooltip\":true,\"addLegend\":true,\"legendPosition\":\"top\",\"isDonut\":false,\"labels\":{\"show\":false,\"values\":true,\"last_level\":true,\"truncate\":100}},\"aggs\":[{\"id\":\"1\",\"enabled\":true,\"type\":\"count\",\"schema\":\"metric\",\"params\":{}},{\"id\":\"2\",\"enabled\":true,\"type\":\"terms\",\"schema\":\"segment\",\"params\":{\"field\":\"krb5.sname.keyword\",\"size\":10,\"order\":\"desc\",\"orderBy\":\"1\",\"otherBucket\":false,\"otherBucketLabel\":\"Other\",\"missingBucket\":false,\"missingBucketLabel\":\"Missing\"}}]}"
    }
}