{
    "migrationVersion": {
        "visualization": "6.7.2"
    }, 
    "type": "visualization", 
    "updated_at": "2019-10-06T09:52:20.603Z", 
    "visualization": {
        "description": "", 
        "kibanaSavedObjectMeta": {
            "searchSourceJSON": "{\"index\":\"logstash-ssh-*\",\"query\":{\"query\":{\"query_string\":{\"query\":\"*\",\"analyze_wildcard\":true}},\"language\":\"lucene\"},\"filter\":[]}"
        }, 
        "title": "SSH transactions count", 
        "uiStateJSON": "{}", 
        "version": 1, 
        "visState": "{\"type\":\"metric\",\"params\":{\"fontSize\":60},\"aggs\":[{\"id\":\"1\",\"type\":\"count\",\"schema\":\"metric\",\"params\":{}}],\"listeners\":{},\"title\":\"SSH transactions count\"}"
    }
}